dcllottery/__init__.py
dcllottery/utils.py
dcllottery-0.1.data/scripts/dcl-lottery
dcllottery-0.1.dist-info/LICENSE
dcllottery-0.1.dist-info/METADATA
dcllottery-0.1.dist-info/WHEEL
dcllottery-0.1.dist-info/top_level.txt
dcllottery-0.1.dist-info/RECORD
