Metadata-Version: 2.1
Name: dcllottery
Version: 0.1
Summary: Lottery utility package
Home-page: https://github.com/deepcloudlabs/lottery
Author: Binnur Kurt
Author-email: info@deepcloudlabs.com
License: UNKNOWN
Platform: UNKNOWN
Classifier: Programming Language :: Python :: 3
Classifier: License :: OSI Approved :: MIT License
Classifier: Operating System :: OS Independent
Requires-Python: >=3.6
License-File: LICENSE
